simcubeltd_pulumi_onepassword
