Metadata-Version: 2.1
Name: simcubeltd-pulumi-onepassword
Version: 1.0.3
Summary: A Pulumi package for creating and managing onepassword resources.
Home-page: https://github.com/SimCubeLtd/pulumi-onepassword
License: MIT
Project-URL: Repository, https://github.com/SimCubeLtd/pulumi-onepassword
Keywords: pulumi onepassword category/cloud
Platform: UNKNOWN
